setup.py
rpdsnd_distributions/Binomialdistribution.py
rpdsnd_distributions/Gaussiandistribution.py
rpdsnd_distributions/Generaldistribution.py
rpdsnd_distributions/__init__.py
rpdsnd_distributions.egg-info/PKG-INFO
rpdsnd_distributions.egg-info/SOURCES.txt
rpdsnd_distributions.egg-info/dependency_links.txt
rpdsnd_distributions.egg-info/not-zip-safe
rpdsnd_distributions.egg-info/top_level.txt