Metadata-Version: 1.0
Name: rpdsnd-distributions
Version: 1.0
Summary: Gaussian and Binomial distributions
Home-page: UNKNOWN
Author: Rabin Paudel
Author-email: rabin.paudel@gmail.com
License: UNKNOWN
Platform: UNKNOWN
